{"query":"lazada","results":[{"t":"Lazada Philippines: Shop online up to 90% off Branded ...","u":"https:\/\/www.lazada.com.ph\/","d":"lazada.com.ph","p":"Shop amazing deals with stackable vouchers for bigger discounts at Lazada.com.ph | Fast and Free Shipping \u2713 Pay via Lazada Wallet \u2713 Effortless Shopping!"},{"t":"Lazada","u":"https:\/\/www.lazada.com\/","d":"lazada.com","p":"With Lazada, any business can scale and become a super eBusiness. Let our digital capabilities enable your ambitions as you grow in the region. Find out more\u00a0..."}]}