{"query":"luke tittensor","results":[{"t":"Luke Tittensor","u":"https:\/\/en.wikipedia.org\/wiki\/Luke_Tittensor","d":"en.wikipedia.org","p":""},{"t":"Luke Tittensor","u":"https:\/\/www.imdb.com\/name\/nm1340109\/","d":"imdb.com","p":""},{"t":"Luke Tittensor - Shameless Wiki - Fandom","u":"https:\/\/shameless.fandom.com\/wiki\/Luke_Tittensor","d":"shameless.fandom.com","p":"Luke James Tittensor was born on November 3, 1989, in Heywood, Greater Manchester. He is an actor best known for playing Daz Eden in the ITV soap Emmerdale."},{"t":"Luke Tittensor - Wiki of Westeros - Fandom","u":"https:\/\/gameofthrones.fandom.com\/wiki\/Luke_Tittensor","d":"gameofthrones.fandom.com","p":""},{"t":"Luke Tittensor - Biography","u":"https:\/\/www.imdb.com\/name\/nm1340109\/bio\/","d":"imdb.com","p":""},{"t":"'House of the Dragon': Elliott and Luke Tittensor on That ...","u":"https:\/\/www.nytimes.com\/2024\/06\/24\/arts\/television\/house-of-the-dragon-twins-elliott-luke-tittensor.html","d":"nytimes.com","p":""},{"t":"Luke Tittensor","u":"https:\/\/www.themoviedb.org\/person\/1227875-luke-tittensor","d":"themoviedb.org","p":""},{"t":"Elliott Tittensor","u":"https:\/\/en.wikipedia.org\/wiki\/Elliott_Tittensor","d":"en.wikipedia.org","p":""},{"t":"75 Luke Tittensor Photos & High Res Pictures","u":"https:\/\/www.gettyimages.com\/photos\/luke-tittensor","d":"gettyimages.com","p":"Browse Getty Images' premium collection of high-quality, authentic Luke Tittensor photos & royalty-free pictures, taken by professional Getty Images\u00a0..."},{"t":"Child star Luke Tittensor unrecognisable 15 years on from ...","u":"https:\/\/metro.co.uk\/2024\/06\/12\/emmerdale-child-star-luke-tittensor-unrecognisable-15-years-role-21017640\/","d":"metro.co.uk","p":""}]}