{"query":"wolf","results":[{"t":"Wolf","u":"https:\/\/en.wikipedia.org\/wiki\/Wolf","d":"en.wikipedia.org","p":""},{"t":"The Social Wolf - Living with Wolves","u":"https:\/\/www.livingwithwolves.org\/about-wolves\/social-wolf\/#:~:text=Wolves%20are%20complex%2C%20highly%20intelligent,and%20live%20in%20family%20groups.","d":"livingwithwolves.org","p":""},{"t":"Wolf | Species & Facts","u":"https:\/\/www.britannica.com\/animal\/wolf","d":"britannica.com","p":""},{"t":"Gray Wolf","u":"https:\/\/www.nationalgeographic.com\/animals\/mammals\/facts\/gray-wolf","d":"nationalgeographic.com","p":""},{"t":"Wolf Definition & Meaning","u":"https:\/\/www.merriam-webster.com\/dictionary\/wolf","d":"merriam-webster.com","p":""},{"t":"Wolf (1994)","u":"https:\/\/www.imdb.com\/title\/tt0111742\/","d":"imdb.com","p":""},{"t":"Gray Wolf","u":"https:\/\/www.nwf.org\/Educational-Resources\/Wildlife-Guide\/Mammals\/Gray-Wolf","d":"nwf.org","p":""},{"t":"Wolf - Simple English Wikipedia, the free encyclopedia","u":"https:\/\/simple.wikipedia.org\/wiki\/Wolf","d":"simple.wikipedia.org","p":""},{"t":"Gray wolf | Size, Habitat, Diet, Predators, & Facts","u":"https:\/\/www.britannica.com\/animal\/gray-wolf","d":"britannica.com","p":""},{"t":"Gray Wolf (Canis lupus) | U.S. Fish & Wildlife Service","u":"https:\/\/www.fws.gov\/species\/gray-wolf-canis-lupus","d":"fws.gov","p":""}]}