{"query":"sons of the forest","results":[{"t":"Sons of the Forest","u":"https:\/\/store.steampowered.com\/app\/1326470\/Sons_Of_The_Forest\/","d":"store.steampowered.com","p":""},{"t":"Sons of the Forest","u":"https:\/\/en.wikipedia.org\/wiki\/Sons_of_the_Forest","d":"en.wikipedia.org","p":""},{"t":"Sons of the Forest - Wikipedia","u":"https:\/\/en.wikipedia.org\/wiki\/Sons_of_the_Forest#:~:text=Serving%20as%20the%20sequel%20to,ancient%20secret%20buried%20deep%20underground.","d":"en.wikipedia.org","p":""},{"t":"Sons of the Forest Review","u":"https:\/\/www.ign.com\/articles\/sons-of-the-forest-review","d":"ign.com","p":""},{"t":"Sons Of The Forest","u":"https:\/\/steamcommunity.com\/app\/1326470","d":"steamcommunity.com","p":""},{"t":"Sons of the Forest Wiki - Fandom","u":"https:\/\/sonsoftheforest.fandom.com\/wiki\/Sons_of_the_Forest_Wiki","d":"sonsoftheforest.fandom.com","p":""},{"t":"Sons Of The Forest review: beautiful survival horror with a ...","u":"https:\/\/www.rockpapershotgun.com\/sons-of-the-forest-review","d":"rockpapershotgun.com","p":""},{"t":"r\/SonsOfTheForest","u":"https:\/\/www.reddit.com\/r\/SonsOfTheForest\/","d":"reddit.com","p":"r\/SonsOfTheForest: The official subreddit of the game Sons of The Forest! Discuss all things SOTF here. r\/TheForest for the prequel, The Forest!"},{"t":"Endnight Games","u":"https:\/\/endnightgames.com\/","d":"endnightgames.com","p":""}]}