{"query":"amd","results":[{"t":"AMD \u05c0 together we advance_AI","u":"https:\/\/www.amd.com\/en.html","d":"amd.com","p":"AMD delivers leadership high-performance and adaptive computing solutions to advance data center AI, AI PCs, intelligent edge devices, gaming, & beyond."},{"t":"Drivers and Support for Processors and Graphics","u":"https:\/\/www.amd.com\/en\/support\/download\/drivers.html","d":"amd.com","p":"Drivers and Support for Processors and Graphics \u00b7 Windows\u00ae 10\/11 Drivers \u00b7 Linux Drivers \u00b7 Search or Browse Drivers and Support by Product \u00b7 More Resources\u00a0..."}]}