{"query":"nextjs","results":[{"t":"Next.js by Vercel - The React Framework","u":"https:\/\/nextjs.org\/","d":"nextjs.org","p":"Used by some of the world's largest companies, Next.js enables you to create high-quality web applications with the power of React components."},{"t":"Next.js by Vercel - The React Framework","u":"https:\/\/nextjs.org\/#:~:text=Next.js%20by%20Vercel%20%2D%20The%20React%20Framework&text=The%20React%20Framework%20for%20the,the%20power%20of%20React%20components.","d":"nextjs.org","p":"r\/nextjs: Next.js is a React framework for building full-stack web applications."}]}